lawsql_justice/__init__.py
lawsql_justice/patterns.py
lawsql_justice/surname.py
lawsql_justice/typos.py
lawsql_justice-0.0.1.dist-info/WHEEL
lawsql_justice-0.0.1.dist-info/METADATA
lawsql_justice-0.0.1.dist-info/RECORD
